[
    {
        "key": "dbln",
        "value": "%7B%2261560112174902%22%3A%22psoYgdIx%22%7D",
        "domain": "facebook.com",
        "path": "/login/device-based/",
        "hostOnly": false,
        "creation": "2026-04-27T16:34:44.146Z",
        "lastAccessed": "2026-04-27T16:34:44.147Z"
    },
    {
        "key": "datr",
        "value": "-ADMaWXTR--ZF1qSR5r9LbuB",
        "domain": "facebook.com",
        "path": "/",
        "hostOnly": false,
        "creation": "2026-04-27T16:34:44.147Z",
        "lastAccessed": "2026-04-27T16:34:44.147Z"
    },
    {
        "key": "sb",
        "value": "-ADMaUiuvERCablFi1TQ471p",
        "domain": "facebook.com",
        "path": "/",
        "hostOnly": false,
        "creation": "2026-04-27T16:34:44.147Z",
        "lastAccessed": "2026-04-27T16:34:44.147Z"
    },
    {
        "key": "dpr",
        "value": "3.0234789848327637",
        "domain": "facebook.com",
        "path": "/",
        "hostOnly": false,
        "creation": "2026-04-27T16:34:44.147Z",
        "lastAccessed": "2026-04-27T16:34:44.147Z"
    },
    {
        "key": "ps_l",
        "value": "1",
        "domain": "facebook.com",
        "path": "/",
        "hostOnly": false,
        "creation": "2026-04-27T16:34:44.147Z",
        "lastAccessed": "2026-04-27T16:34:44.147Z"
    },
    {
        "key": "ps_n",
        "value": "1",
        "domain": "facebook.com",
        "path": "/",
        "hostOnly": false,
        "creation": "2026-04-27T16:34:44.147Z",
        "lastAccessed": "2026-04-27T16:34:44.147Z"
    },
    {
        "key": "locale",
        "value": "en_US",
        "domain": "facebook.com",
        "path": "/",
        "hostOnly": false,
        "creation": "2026-04-27T16:34:44.147Z",
        "lastAccessed": "2026-04-27T16:34:44.147Z"
    },
    {
        "key": "wd",
        "value": "891x1601",
        "domain": "facebook.com",
        "path": "/",
        "hostOnly": false,
        "creation": "2026-04-27T16:34:44.147Z",
        "lastAccessed": "2026-04-27T16:34:44.147Z"
    },
    {
        "key": "c_user",
        "value": "61560112174902",
        "domain": "facebook.com",
        "path": "/",
        "hostOnly": false,
        "creation": "2026-04-27T16:34:44.147Z",
        "lastAccessed": "2026-04-27T16:34:44.147Z"
    },
    {
        "key": "xs",
        "value": "7%3AQVBdd7R18WlxvQ%3A2%3A1777307612%3A-1%3A-1%3A%3AAcxm2t7Pzs5dvC9Cg8qUjXrK8lTk0i9_L23XBKzMIQ",
        "domain": "facebook.com",
        "path": "/",
        "hostOnly": false,
        "creation": "2026-04-27T16:34:44.148Z",
        "lastAccessed": "2026-04-27T16:34:44.148Z"
    },
    {
        "key": "fr",
        "value": "1ljRdgxlOLAkJ5HpU.AWcUK7skxyMInW1tF8NN2R2x9M36_QWe0GwAwetWnTXzflyEPgs.Bp74_q..AAA.0.0.Bp75AI.AWfTB8bxQjN3gDmowXYRnQC56SY",
        "domain": "facebook.com",
        "path": "/",
        "hostOnly": false,
        "creation": "2026-04-27T16:34:44.148Z",
        "lastAccessed": "2026-04-27T16:34:44.148Z"
    },
    {
        "key": "presence",
        "value": "C%7B%22t3%22%3A%5B%5D%2C%22utc3%22%3A1777307669291%2C%22v%22%3A1%7D",
        "domain": "facebook.com",
        "path": "/",
        "hostOnly": false,
        "creation": "2026-04-27T16:34:44.148Z",
        "lastAccessed": "2026-04-27T16:34:44.148Z"
    }
]