[
    {
        "key": "dbln",
        "value": "%7B%2261577872439503%22%3A%22cJcwIznD%22%7D",
        "domain": "facebook.com",
        "path": "/login/device-based/",
        "hostOnly": false,
        "creation": "2026-02-23T06:55:36.132Z",
        "lastAccessed": "2026-02-23T06:55:36.133Z"
    },
    {
        "key": "datr",
        "value": "YssFaYGNVcHcFVhREfpwzbYB",
        "domain": "facebook.com",
        "path": "/",
        "hostOnly": false,
        "creation": "2026-02-23T06:55:36.133Z",
        "lastAccessed": "2026-02-23T06:55:36.133Z"
    },
    {
        "key": "sb",
        "value": "YssFaXcmfCM7uv53xYfAESvI",
        "domain": "facebook.com",
        "path": "/",
        "hostOnly": false,
        "creation": "2026-02-23T06:55:36.133Z",
        "lastAccessed": "2026-02-23T06:55:36.133Z"
    },
    {
        "key": "ps_l",
        "value": "1",
        "domain": "facebook.com",
        "path": "/",
        "hostOnly": false,
        "creation": "2026-02-23T06:55:36.133Z",
        "lastAccessed": "2026-02-23T06:55:36.133Z"
    },
    {
        "key": "ps_n",
        "value": "1",
        "domain": "facebook.com",
        "path": "/",
        "hostOnly": false,
        "creation": "2026-02-23T06:55:36.133Z",
        "lastAccessed": "2026-02-23T06:55:36.133Z"
    },
    {
        "key": "wl_cbv",
        "value": "v2%3Bclient_version%3A3013%3Btimestamp%3A1765373438",
        "domain": "facebook.com",
        "path": "/",
        "hostOnly": false,
        "creation": "2026-02-23T06:55:36.133Z",
        "lastAccessed": "2026-02-23T06:55:36.133Z"
    },
    {
        "key": "pas",
        "value": "61577872439503%3AgYCpa5GnGp%2C61560112174902%3ACqQEEDMwol",
        "domain": "facebook.com",
        "path": "/",
        "hostOnly": false,
        "creation": "2026-02-23T06:55:36.133Z",
        "lastAccessed": "2026-02-23T06:55:36.133Z"
    },
    {
        "key": "dpr",
        "value": "3.0234789848327637",
        "domain": "facebook.com",
        "path": "/",
        "hostOnly": false,
        "creation": "2026-02-23T06:55:36.133Z",
        "lastAccessed": "2026-02-23T06:55:36.133Z"
    },
    {
        "key": "locale",
        "value": "en_GB",
        "domain": "facebook.com",
        "path": "/",
        "hostOnly": false,
        "creation": "2026-02-23T06:55:36.133Z",
        "lastAccessed": "2026-02-23T06:55:36.133Z"
    },
    {
        "key": "wd",
        "value": "891x1601",
        "domain": "facebook.com",
        "path": "/",
        "hostOnly": false,
        "creation": "2026-02-23T06:55:36.133Z",
        "lastAccessed": "2026-02-23T06:55:36.133Z"
    },
    {
        "key": "c_user",
        "value": "61560112174902",
        "domain": "facebook.com",
        "path": "/",
        "hostOnly": false,
        "creation": "2026-02-23T06:55:36.133Z",
        "lastAccessed": "2026-02-23T06:55:36.133Z"
    },
    {
        "key": "xs",
        "value": "29%3Atr92UNJcZsxq-g%3A2%3A1771829493%3A-1%3A-1%3A%3AAcyXEv2lnr-QhCe6pe6jfAgwDo9FSbbaiy2I1AV76A",
        "domain": "facebook.com",
        "path": "/",
        "hostOnly": false,
        "creation": "2026-02-23T06:55:36.133Z",
        "lastAccessed": "2026-02-23T06:55:36.133Z"
    },
    {
        "key": "fr",
        "value": "1VFNXQspS1HXdfn4C.AWfTrHagTdkhxEjtj1WTxFAX1_OXPcdVrfmM7euKlr_9wE-c-mY.Bpm_nO..AAA.0.0.Bpm_nO.AWdO-lBC-251_AM70b7-C3-1q1s",
        "domain": "facebook.com",
        "path": "/",
        "hostOnly": false,
        "creation": "2026-02-23T06:55:36.133Z",
        "lastAccessed": "2026-02-23T06:55:36.133Z"
    },
    {
        "key": "presence",
        "value": "C%7B%22t3%22%3A%5B%5D%2C%22utc3%22%3A1771829719835%2C%22v%22%3A1%7D",
        "domain": "facebook.com",
        "path": "/",
        "hostOnly": false,
        "creation": "2026-02-23T06:55:36.133Z",
        "lastAccessed": "2026-02-23T06:55:36.133Z"
    }
]